
{
    "package": {
        "name": "OpenHab", 
        "repo": "OpenHab",
        "subject": "yglazko/OpenHab", 
        "desc": "Vaani OpenHab submodule",
        "website_url": "www.vaani.iot",
        "issue_tracker_url": "https://github.com/bintray/bintray-client-java/issues",
        "vcs_url": "https://github.com/bintray/bintray-client-java.git",
        "github_use_tag_release_notes": true,
        "github_release_notes_file": "README.md",
        "licenses": ["IDK"],
        "labels": ["cool", "awesome", "gorilla"],
        "public_download_numbers": false,
        "public_stats": false,
        }

    "version": {
        "name": "0.5"
    },

    "files":
        [
        {"includePattern": "build/bin(.*)*/(.*\.gem)", "excludePattern": ".*/do-not-deploy/.*", "uploadPattern": "gems/$2"},
        {"includePattern": "build/docs/(.*)", "uploadPattern": "docs/$1"}
        ],
    "publish": true
}
